killtracker/__init__.py
killtracker/admin.py
killtracker/app_settings.py
killtracker/apps.py
killtracker/checks.py
killtracker/constants.py
killtracker/forms.py
killtracker/managers.py
killtracker/providers.py
killtracker/signals.py
killtracker/tasks.py
killtracker/core/__init__.py
killtracker/core/discord.py
killtracker/core/helpers.py
killtracker/core/trackers.py
killtracker/core/workers.py
killtracker/core/zkb.py
killtracker/management/commands/killtracker_load_eve.py
killtracker/migrations/0001_initial_new.py
killtracker/migrations/0001_squashed_all.py
killtracker/migrations/0002_fix_webhook_notes_field.py
killtracker/migrations/0002_tracker_require_attackers_weapon_groups_and_more.py
killtracker/migrations/0003_add_state_clauses.py
killtracker/migrations/0003_optimize_tracker_form.py
killtracker/migrations/0004_add_faction_clauses.py
killtracker/migrations/0004_django4_update.py
killtracker/migrations/0005_add_final_blow_clause_and_more.py
killtracker/migrations/0005_war_kills.py
killtracker/migrations/0006_evetypeplus.py
killtracker/migrations/0007_restructure_killsmails.py
killtracker/migrations/0008_copy_data_to_new_structure.py
killtracker/migrations/0009_remove_old_models.py
killtracker/migrations/__init__.py
killtracker/models/__init__.py
killtracker/models/killmails.py
killtracker/models/trackers.py
killtracker/models/webhooks.py
killtracker/static/killtracker/killtracker_logo.png
killtracker/static/killtracker/zkb_icon.png
killtracker/templates/admin/killtracker/tracker/killmail_test.html
killtracker/tests/__init__.py
killtracker/tests/test_admin.py
killtracker/tests/test_admin_2.py
killtracker/tests/test_integration.py
killtracker/tests/test_tasks.py
killtracker/tests/core/__init__.py
killtracker/tests/core/test_discord.py
killtracker/tests/core/test_helpers.py
killtracker/tests/core/test_tracker_1.py
killtracker/tests/core/test_tracker_2.py
killtracker/tests/core/test_workers.py
killtracker/tests/core/test_zkb.py
killtracker/tests/models/__init__.py
aa_killtracker-1.2.1.dist-info/licenses/LICENSE
aa_killtracker-1.2.1.dist-info/WHEEL
aa_killtracker-1.2.1.dist-info/METADATA
aa_killtracker-1.2.1.dist-info/RECORD
